pocketeer/__init__.py
pocketeer/api.py
pocketeer/cli.py
pocketeer/vis.py
pocketeer/core/__init__.py
pocketeer/core/clustering.py
pocketeer/core/geometry.py
pocketeer/core/scoring.py
pocketeer/core/tessellation.py
pocketeer/core/types.py
pocketeer/utils/__init__.py
pocketeer/utils/constants.py
pocketeer/utils/exceptions.py
pocketeer/utils/io.py
pocketeer-0.2.0.dist-info/METADATA
pocketeer-0.2.0.dist-info/WHEEL
pocketeer-0.2.0.dist-info/entry_points.txt
pocketeer-0.2.0.dist-info/licenses/LICENSE
pocketeer-0.2.0.dist-info/RECORD
