Metadata-Version: 2.4
Name: pocketeer
Version: 0.2.0
Summary: A minimal, fpocket-style pocket finder in pure Python/Numpy.
Project-URL: Homepage, https://github.com/cch1999/pocketeer
Project-URL: Repository, https://github.com/cch1999/pocketeer
Project-URL: Documentation, https://pocketeer.readthedocs.io
Project-URL: Issues, https://github.com/cch1999/pocketeer/issues
Author-email: Charlie Harris <cch57@cam.ac.uk>
License: MIT
License-File: LICENSE
Keywords: alpha-sphere,binding-site,bioinformatics,delaunay,fpocket,pocket,protein,structural-biology
Classifier: Development Status :: 4 - Beta
Classifier: Intended Audience :: Science/Research
Classifier: License :: OSI Approved :: MIT License
Classifier: Operating System :: OS Independent
Classifier: Programming Language :: Python :: 3
Classifier: Programming Language :: Python :: 3.11
Classifier: Programming Language :: Python :: 3.12
Classifier: Topic :: Scientific/Engineering :: Bio-Informatics
Classifier: Topic :: Scientific/Engineering :: Chemistry
Requires-Python: >=3.11
Requires-Dist: biotite>=0.40
Requires-Dist: numba>=0.59
Requires-Dist: numpy>=1.24
Requires-Dist: rich>=13.0
Requires-Dist: scipy>=1.10
Requires-Dist: typer>=0.19.2
Provides-Extra: dev
Requires-Dist: interrogate>=1.7.0; extra == 'dev'
Requires-Dist: ipykernel>=7.1.0; extra == 'dev'
Requires-Dist: justfile>=0.0.1a0; extra == 'dev'
Requires-Dist: pytest-xdist>=3.8.0; extra == 'dev'
Requires-Dist: pytest>=7.0; extra == 'dev'
Requires-Dist: ruff>=0.1.0; extra == 'dev'
Requires-Dist: ty>=0.0.1a21; extra == 'dev'
Provides-Extra: docs
Requires-Dist: mkdocs-material>=9.0.0; extra == 'docs'
Requires-Dist: mkdocs>=1.6.1; extra == 'docs'
Provides-Extra: vis
Requires-Dist: atomworks>=1.0.3; extra == 'vis'
Requires-Dist: dotenv>=0.9.9; extra == 'vis'
